coverforest-0.0.3.dist-info/RECORD
coverforest-0.0.3.dist-info/METADATA
coverforest-0.0.3.dist-info/WHEEL
coverforest-0.0.3.dist-info/top_level.txt
coverforest-0.0.3.dist-info/LICENSE
meson/meson.py
coverforest/_fast_random_forest.py
coverforest/metrics.py
coverforest/_forest.py
coverforest/_version.py
coverforest/_giqs.cpython-312-x86_64-linux-gnu.so
coverforest/__init__.py
doc/_templates/numpydoc_docstring.py
coverforest.libs/libgomp-a34b3233.so.1.0.0
