Metadata-Version: 2.2
Name: coverforest
Version: 0.0.3
Summary: A simple and fast sklearn-compatible conformal predictions with random forests for both classification and regression tasks.
Author-email: Donlapark Ponnoprat <donlapark@gmail.com>
Project-URL: Homepage, https://github.com/donlapark/coverforest
Project-URL: Issues, https://github.com/donlapark/coverforest/issues
Classifier: Programming Language :: Python :: 3
Classifier: Programming Language :: Python :: 3.9
Classifier: Programming Language :: Python :: 3.10
Classifier: Programming Language :: Python :: 3.11
Classifier: Programming Language :: Python :: 3.12
Classifier: License :: OSI Approved :: BSD License
Classifier: Operating System :: POSIX
Classifier: Operating System :: Unix
Classifier: Operating System :: MacOS
Classifier: Operating System :: Microsoft :: Windows
Requires-Python: >=3.9
License-File: LICENSE
Requires-Dist: scikit-learn>=1.6.0
